mm_print/__init__.py
mm_print/output.py
mm_print/py.typed
mm_print-0.2.2.dist-info/METADATA
mm_print-0.2.2.dist-info/WHEEL
mm_print-0.2.2.dist-info/RECORD
