Metadata-Version: 2.4
Name: mm-print
Version: 0.2.2
Summary: Enhanced printing library with rich formatting support.
Requires-Python: >=3.13
Requires-Dist: mm-std~=0.6.0
Requires-Dist: rich~=14.2.0
Requires-Dist: tomlkit~=0.13.0
